lukhed_x/__init__.py
lukhed_x/x_api.py
lukhed_x-0.1.2.dist-info/LICENSE
lukhed_x-0.1.2.dist-info/METADATA
lukhed_x-0.1.2.dist-info/WHEEL
lukhed_x-0.1.2.dist-info/top_level.txt
lukhed_x-0.1.2.dist-info/RECORD
