Metadata-Version: 2.1
Name: lukhed-x
Version: 0.1.2
Summary: Custom tweepy wrapper for posting on X. Used by @grindSunday and @popPunkpoets Bots
Home-page: https://github.com/lukhed/lukhed_x
Author: lukhed
Author-email: lukhed.mail@gmail.com
Classifier: Programming Language :: Python :: 3
Classifier: License :: OSI Approved :: MIT License
Classifier: Operating System :: OS Independent
Requires-Python: >=3.9
License-File: LICENSE
Requires-Dist: lukhed-basic-utils>=1.6.4
Requires-Dist: tweepy>=4.16.0
